{"4fd272c78eb7c8105d82f71a": {"_id": "4fd272c78eb7c8105d82f71a", "headline": "Corrections", "keyword_org_rank_alt": 0.25, "headline_summary_senti": -0.2263, "summary_senti": -0.2263, "headline_senti": 0.0, "trade_date": "2007-01-04", "lead_paragraph_senti": -0.4019, "pub_date": "2007-01-04T00:00:00Z", "keyword_in_summary": 0, "keyword_in_headline": 0}, "4fd279c88eb7c8105d83d504": {"_id": "4fd279c88eb7c8105d83d504", "headline": "Art in Review; Michael Fullerton", "keyword_org_rank_alt": 0.0, "headline_summary_senti": 0.0, "summary_senti": 0.0, "headline_senti": 0.0, "trade_date": "2007-01-12", "lead_paragraph_senti": 0.1901, "pub_date": "2007-01-12T00:00:00Z", "keyword_in_summary": 0, "keyword_in_headline": 0}, "548d74eb38f0d80cddfa0a11": {"_id": "548d74eb38f0d80cddfa0a11", "headline": "Who Is Best at R&D?", "keyword_org_rank_alt": 0.5, "headline_summary_senti": 0.8481, "summary_senti": 0.6124, "headline_senti": 0.6369, "trade_date": "2007-01-08", "lead_paragraph_senti": 0.6124, "pub_date": "2007-01-06T00:00:00Z", "keyword_in_summary": 1, "keyword_in_headline": 0}, "4fd366f68eb7c8105d8b6e93": {"_id": "4fd366f68eb7c8105d8b6e93", "headline": "The Password Is\u2026 Everywhere", "keyword_org_rank_alt": 0.0, "headline_summary_senti": 0.7414, "summary_senti": 0.7414, "headline_senti": 0.0, "trade_date": "2007-01-29", "lead_paragraph_senti": 0.539, "pub_date": "2007-01-27T10:35:56Z", "keyword_in_summary": 1, "keyword_in_headline": 0}, "4fd255c38eb7c8105d7fea53": {"_id": "4fd255c38eb7c8105d7fea53", "headline": "TODAY IN BUSINESS", "keyword_org_rank_alt": 0.0, "headline_summary_senti": 0.0, "summary_senti": 0.0, "headline_senti": 0.0, "trade_date": "2007-01-01", "lead_paragraph_senti": 0.7959, "pub_date": "2007-01-01T00:00:00Z", "keyword_in_summary": 0, "keyword_in_headline": 0}, "4fd3675d8eb7c8105d8b7599": {"_id": "4fd3675d8eb7c8105d8b7599", "headline": "News Quiz: Final Passages", "keyword_org_rank_alt": 0.0, "headline_summary_senti": 0.0, "summary_senti": 0.0, "headline_senti": 0.0, "trade_date": "2007-01-08", "lead_paragraph_senti": 0.7346, "pub_date": "2007-01-07T20:59:55Z", "keyword_in_summary": 0, "keyword_in_headline": 0}, "4fd28d5f8eb7c8105d8631fa": {"_id": "4fd28d5f8eb7c8105d8631fa", "headline": "Corrections", "keyword_org_rank_alt": 1.0, "headline_summary_senti": 0.0, "summary_senti": 0.0, "headline_senti": 0.0, "trade_date": "2007-01-05", "lead_paragraph_senti": 0.0, "pub_date": "2007-01-05T00:00:00Z", "keyword_in_summary": 1, "keyword_in_headline": 0}, "4fd366f38eb7c8105d8b6d83": {"_id": "4fd366f38eb7c8105d8b6d83", "headline": "Lobbyists Ask for Delay on N.Y.S.E. Data Fees Ruling", "keyword_org_rank_alt": 0.0, "headline_summary_senti": -0.2023, "summary_senti": 0.128, "headline_senti": -0.3182, "trade_date": "2007-01-23", "lead_paragraph_senti": 0.4588, "pub_date": "2007-01-23T13:20:27Z", "keyword_in_summary": 0, "keyword_in_headline": 0}, "4fd255c58eb7c8105d7fec3b": {"_id": "4fd255c58eb7c8105d7fec3b", "headline": "World Business Briefing | Europe: Britain: BBC In Talks With Youtube", "keyword_org_rank_alt": 0.3333333333333333, "headline_summary_senti": 0.0, "summary_senti": 0.0, "headline_senti": 0.0, "trade_date": "2007-01-23", "lead_paragraph_senti": 0.0, "pub_date": "2007-01-23T00:00:00Z", "keyword_in_summary": 1, "keyword_in_headline": 0}, "4fd28d618eb7c8105d8632ff": {"_id": "4fd28d618eb7c8105d8632ff", "headline": "TODAY IN BUSINESS", "keyword_org_rank_alt": 0.0, "headline_summary_senti": 0.3818, "summary_senti": 0.3818, "headline_senti": 0.0, "trade_date": "2007-01-31", "lead_paragraph_senti": 0.9874, "pub_date": "2007-01-31T00:00:00Z", "keyword_in_summary": 0, "keyword_in_headline": 0}, "4fd3670f8eb7c8105d8b707f": {"_id": "4fd3670f8eb7c8105d8b707f", "headline": "Google\u2019s High-Octane Mixer", "keyword_org_rank_alt": 0.0, "headline_summary_senti": 0.8689, "summary_senti": 0.8689, "headline_senti": 0.0, "trade_date": "2007-01-23", "lead_paragraph_senti": 0.4019, "pub_date": "2007-01-23T18:20:23Z", "keyword_in_summary": 1, "keyword_in_headline": 1}, "4fd367278eb7c8105d8b72a1": {"_id": "4fd367278eb7c8105d8b72a1", "headline": "Apple, Google and Napster Named in Patent Lawsuit", "keyword_org_rank_alt": 0.0, "headline_summary_senti": 0.0, "summary_senti": 0.2263, "headline_senti": -0.2263, "trade_date": "2007-01-03", "lead_paragraph_senti": -0.2263, "pub_date": "2007-01-03T07:27:24Z", "keyword_in_summary": 1, "keyword_in_headline": 1}, "4fd367278eb7c8105d8b72c8": {"_id": "4fd367278eb7c8105d8b72c8", "headline": "Spinning Google and YouTube Into Gold", "keyword_org_rank_alt": 0.0, "headline_summary_senti": 0.5106, "summary_senti": 0.5106, "headline_senti": 0.0, "trade_date": "2007-01-26", "lead_paragraph_senti": 0.5106, "pub_date": "2007-01-26T12:11:10Z", "keyword_in_summary": 1, "keyword_in_headline": 1}, "548d545638f0d80cddfa072f": {"_id": "548d545638f0d80cddfa072f", "headline": "Patent Lawsuit Names Leading Technology Firms", "keyword_org_rank_alt": 0.25, "headline_summary_senti": -0.5574, "summary_senti": -0.4019, "headline_senti": -0.2263, "trade_date": "2007-01-03", "lead_paragraph_senti": -0.4019, "pub_date": "2007-01-03T00:00:00Z", "keyword_in_summary": 1, "keyword_in_headline": 0}, "4fd272c78eb7c8105d82f753": {"_id": "4fd272c78eb7c8105d82f753", "headline": "World Business Briefing | Asia: China: Google Invests In Internet Firm", "keyword_org_rank_alt": 0.5, "headline_summary_senti": 0.0, "summary_senti": 0.0, "headline_senti": 0.0, "trade_date": "2007-01-05", "lead_paragraph_senti": 0.6369, "pub_date": "2007-01-05T00:00:00Z", "keyword_in_summary": 1, "keyword_in_headline": 1}, "4fd258e48eb7c8105d804e8a": {"_id": "4fd258e48eb7c8105d804e8a", "headline": "TODAY IN BUSINESS", "keyword_org_rank_alt": 0.0, "headline_summary_senti": 0.2732, "summary_senti": 0.2732, "headline_senti": 0.0, "trade_date": "2007-01-11", "lead_paragraph_senti": 0.9379, "pub_date": "2007-01-11T00:00:00Z", "keyword_in_summary": 1, "keyword_in_headline": 0}, "4fd2552f8eb7c8105d7fd716": {"_id": "4fd2552f8eb7c8105d7fd716", "headline": "News Summary", "keyword_org_rank_alt": 0.0, "headline_summary_senti": -0.296, "summary_senti": -0.296, "headline_senti": 0.0, "trade_date": "2007-01-01", "lead_paragraph_senti": -0.9674, "pub_date": "2007-01-01T00:00:00Z", "keyword_in_summary": 0, "keyword_in_headline": 0}, "548e57ad38f0d8437a5dbd4a": {"_id": "548e57ad38f0d8437a5dbd4a", "headline": "Google Halts \u2018Miserable Failure\u2019 Link to President Bush", "keyword_org_rank_alt": 1.0, "headline_summary_senti": 0.0, "summary_senti": 0.0, "headline_senti": 0.0, "trade_date": "2007-01-29", "lead_paragraph_senti": 0.0, "pub_date": "2007-01-29T00:00:00Z", "keyword_in_summary": 1, "keyword_in_headline": 1}, "548d69e438f0d80cddfa0921": {"_id": "548d69e438f0d80cddfa0921", "headline": "Correction: For the Record", "keyword_org_rank_alt": 0.0, "headline_summary_senti": 0.0, "summary_senti": 0.0, "headline_senti": 0.0, "trade_date": "2007-01-05", "lead_paragraph_senti": 0.0, "pub_date": "2007-01-05T00:00:00Z", "keyword_in_summary": 1, "keyword_in_headline": 0}, "548d5d3f38f0d80cddfa07fb": {"_id": "548d5d3f38f0d80cddfa07fb", "headline": "Correction: For the Record", "keyword_org_rank_alt": 0.0, "headline_summary_senti": -0.4019, "summary_senti": -0.4019, "headline_senti": 0.0, "trade_date": "2007-01-04", "lead_paragraph_senti": -0.4019, "pub_date": "2007-01-04T00:00:00Z", "keyword_in_summary": 1, "keyword_in_headline": 0}, "4fd366e88eb7c8105d8b6c4f": {"_id": "4fd366e88eb7c8105d8b6c4f", "headline": "Google Guys Aren\u2019t Writing Off Old Media", "keyword_org_rank_alt": 0.0, "headline_summary_senti": -0.2263, "summary_senti": -0.2263, "headline_senti": 0.0, "trade_date": "2007-01-26", "lead_paragraph_senti": -0.7351, "pub_date": "2007-01-26T16:04:39Z", "keyword_in_summary": 1, "keyword_in_headline": 1}, "4fd3675d8eb7c8105d8b75f6": {"_id": "4fd3675d8eb7c8105d8b75f6", "headline": "Profit Down, Outlook Up at Yahoo", "keyword_org_rank_alt": 0.0, "headline_summary_senti": 0.5729, "summary_senti": 0.204, "headline_senti": 0.4404, "trade_date": "2007-01-24", "lead_paragraph_senti": 0.204, "pub_date": "2007-01-24T06:57:58Z", "keyword_in_summary": 1, "keyword_in_headline": 0}, "4fd2726b8eb7c8105d82f45f": {"_id": "4fd2726b8eb7c8105d82f45f", "headline": "Nuclear Past and Present", "keyword_org_rank_alt": 0.0, "headline_summary_senti": 0.0, "summary_senti": 0.0, "headline_senti": 0.0, "trade_date": "2007-01-12", "lead_paragraph_senti": 0.7526, "pub_date": "2007-01-12T00:00:00Z", "keyword_in_summary": 0, "keyword_in_headline": 0}, "548d9fc638f0d80cddfa0dda": {"_id": "548d9fc638f0d80cddfa0dda", "headline": "Letters: Nuclear Past and Present", "keyword_org_rank_alt": 0.0, "headline_summary_senti": 0.0516, "summary_senti": 0.0516, "headline_senti": 0.0, "trade_date": "2007-01-12", "lead_paragraph_senti": 0.0644, "pub_date": "2007-01-12T00:00:00Z", "keyword_in_summary": 1, "keyword_in_headline": 0}, "548d6e8138f0d80cddfa0989": {"_id": "548d6e8138f0d80cddfa0989", "headline": "Correction: Can Google Come Out to Play?", "keyword_org_rank_alt": 0.0, "headline_summary_senti": 0.0, "summary_senti": 0.0, "headline_senti": 0.34, "trade_date": "2007-01-08", "lead_paragraph_senti": 0.5574, "pub_date": "2007-01-07T00:00:00Z", "keyword_in_summary": 1, "keyword_in_headline": 1}, "548d6e0238f0d80cddfa097e": {"_id": "548d6e0238f0d80cddfa097e", "headline": "China: Google Invests in Internet Firm", "keyword_org_rank_alt": 1.0, "headline_summary_senti": 0.3182, "summary_senti": 0.3182, "headline_senti": 0.0, "trade_date": "2007-01-05", "lead_paragraph_senti": 0.6369, "pub_date": "2007-01-05T00:00:00Z", "keyword_in_summary": 1, "keyword_in_headline": 1}, "4fd2552f8eb7c8105d7fd7d2": {"_id": "4fd2552f8eb7c8105d7fd7d2", "headline": "Correction", "keyword_org_rank_alt": 1.0, "headline_summary_senti": 0.0, "summary_senti": 0.0, "headline_senti": 0.0, "trade_date": "2007-01-08", "lead_paragraph_senti": 0.5574, "pub_date": "2007-01-07T00:00:00Z", "keyword_in_summary": 1, "keyword_in_headline": 0}, "4fd3670f8eb7c8105d8b7050": {"_id": "4fd3670f8eb7c8105d8b7050", "headline": "Google Buys Stake in Chinese Multimedia Site", "keyword_org_rank_alt": 0.0, "headline_summary_senti": 0.7096, "summary_senti": 0.7096, "headline_senti": 0.0, "trade_date": "2007-01-05", "lead_paragraph_senti": 0.7096, "pub_date": "2007-01-05T07:41:08Z", "keyword_in_summary": 1, "keyword_in_headline": 1}, "4fd2afb48eb7c8105d89f043": {"_id": "4fd2afb48eb7c8105d89f043", "headline": "INSIDE", "keyword_org_rank_alt": 0.0, "headline_summary_senti": 0.4404, "summary_senti": 0.4404, "headline_senti": 0.0, "trade_date": "2007-01-01", "lead_paragraph_senti": 0.8016, "pub_date": "2007-01-01T00:00:00Z", "keyword_in_summary": 1, "keyword_in_headline": 0}, "4fd3675d8eb7c8105d8b75ec": {"_id": "4fd3675d8eb7c8105d8b75ec", "headline": "Davos in the Papers: Google, Trade Talks, Dark Rooms", "keyword_org_rank_alt": 0.0, "headline_summary_senti": 0.0, "summary_senti": 0.0, "headline_senti": 0.0, "trade_date": "2007-01-23", "lead_paragraph_senti": 0.0, "pub_date": "2007-01-23T06:57:55Z", "keyword_in_summary": 1, "keyword_in_headline": 1}, "4fd3675d8eb7c8105d8b75b6": {"_id": "4fd3675d8eb7c8105d8b75b6", "headline": "In Silicon Valley, the Race Is On to Trump Google", "keyword_org_rank_alt": 0.0, "headline_summary_senti": 0.7783, "summary_senti": 0.7783, "headline_senti": 0.0, "trade_date": "2007-01-02", "lead_paragraph_senti": 0.7783, "pub_date": "2007-01-02T07:33:52Z", "keyword_in_summary": 1, "keyword_in_headline": 1}, "4fd258e38eb7c8105d804dd4": {"_id": "4fd258e38eb7c8105d804dd4", "headline": "TODAY IN BUSINESS", "keyword_org_rank_alt": 0.0, "headline_summary_senti": 0.5904, "summary_senti": 0.5904, "headline_senti": 0.0, "trade_date": "2007-01-03", "lead_paragraph_senti": 0.8315, "pub_date": "2007-01-03T00:00:00Z", "keyword_in_summary": 1, "keyword_in_headline": 0}, "4fd366f68eb7c8105d8b6e8c": {"_id": "4fd366f68eb7c8105d8b6e8c", "headline": "Net Pioneer Settles Into 'Nerd Paradise'", "keyword_org_rank_alt": 0.0, "headline_summary_senti": 0.8316, "summary_senti": 0.875, "headline_senti": 0.4588, "trade_date": "2007-01-25", "lead_paragraph_senti": 0.8074, "pub_date": "2007-01-25T13:10:26Z", "keyword_in_summary": 1, "keyword_in_headline": 0}, "4fd3675d8eb7c8105d8b7547": {"_id": "4fd3675d8eb7c8105d8b7547", "headline": "Is 'Little Miss Sunshine' a Used Car?", "keyword_org_rank_alt": 0.0, "headline_summary_senti": 0.4722, "summary_senti": 0.2281, "headline_senti": 0.3848, "trade_date": "2007-01-12", "lead_paragraph_senti": 0.0296, "pub_date": "2007-01-12T14:22:55Z", "keyword_in_summary": 1, "keyword_in_headline": 0}, "4fd366f38eb7c8105d8b6d94": {"_id": "4fd366f38eb7c8105d8b6d94", "headline": "Tech Barons Take on Energy Policy", "keyword_org_rank_alt": 0.0, "headline_summary_senti": 0.9169, "summary_senti": 0.8957, "headline_senti": 0.2732, "trade_date": "2007-01-29", "lead_paragraph_senti": 0.9169, "pub_date": "2007-01-29T07:53:40Z", "keyword_in_summary": 1, "keyword_in_headline": 0}, "4fd366e78eb7c8105d8b6b75": {"_id": "4fd366e78eb7c8105d8b6b75", "headline": "Hospital Closings Mashup", "keyword_org_rank_alt": 0.0, "headline_summary_senti": 0.6705, "summary_senti": 0.6705, "headline_senti": 0.0, "trade_date": "2007-01-16", "lead_paragraph_senti": 0.4019, "pub_date": "2007-01-16T16:08:12Z", "keyword_in_summary": 1, "keyword_in_headline": 0}, "548d77f338f0d80cddfa0a52": {"_id": "548d77f338f0d80cddfa0a52", "headline": "Google Makes Another Investment in the Internet in China", "keyword_org_rank_alt": 1.0, "headline_summary_senti": -0.25, "summary_senti": -0.25, "headline_senti": 0.0, "trade_date": "2007-01-08", "lead_paragraph_senti": -0.25, "pub_date": "2007-01-06T00:00:00Z", "keyword_in_summary": 1, "keyword_in_headline": 1}, "4fd366dc8eb7c8105d8b6ae4": {"_id": "4fd366dc8eb7c8105d8b6ae4", "headline": "Blogtalk", "keyword_org_rank_alt": 0.0, "headline_summary_senti": 0.6415, "summary_senti": 0.6415, "headline_senti": 0.0, "trade_date": "2007-01-04", "lead_paragraph_senti": 0.0, "pub_date": "2007-01-04T14:54:12Z", "keyword_in_summary": 1, "keyword_in_headline": 0}, "548e1e9f38f0d8437a5db802": {"_id": "548e1e9f38f0d8437a5db802", "headline": "Britain: BBC in Talks With YouTube", "keyword_org_rank_alt": 0.0, "headline_summary_senti": 0.0, "summary_senti": 0.0, "headline_senti": 0.0, "trade_date": "2007-01-23", "lead_paragraph_senti": 0.0, "pub_date": "2007-01-23T00:00:00Z", "keyword_in_summary": 1, "keyword_in_headline": 0}, "548d541c38f0d80cddfa072a": {"_id": "548d541c38f0d80cddfa072a", "headline": "Google Answer to Filling Jobs Is an Algorithm", "keyword_org_rank_alt": 1.0, "headline_summary_senti": 0.25, "summary_senti": 0.25, "headline_senti": 0.0, "trade_date": "2007-01-03", "lead_paragraph_senti": 0.25, "pub_date": "2007-01-03T00:00:00Z", "keyword_in_summary": 1, "keyword_in_headline": 1}, "548d42be38f0d80cddfa05a7": {"_id": "548d42be38f0d80cddfa05a7", "headline": "In Silicon Valley, the Race Is On to Trump Google", "keyword_org_rank_alt": 0.25, "headline_summary_senti": 0.3612, "summary_senti": 0.3612, "headline_senti": 0.0, "trade_date": "2007-01-01", "lead_paragraph_senti": 0.3612, "pub_date": "2007-01-01T00:00:00Z", "keyword_in_summary": 1, "keyword_in_headline": 1}, "4fd367768eb7c8105d8b7910": {"_id": "4fd367768eb7c8105d8b7910", "headline": "Brightcove Uploads $59.5 Million in Funding", "keyword_org_rank_alt": 0.0, "headline_summary_senti": 0.0, "summary_senti": 0.0, "headline_senti": 0.0, "trade_date": "2007-01-18", "lead_paragraph_senti": 0.0, "pub_date": "2007-01-18T07:27:14Z", "keyword_in_summary": 1, "keyword_in_headline": 0}, "4fd2b0318eb7c8105d89f387": {"_id": "4fd2b0318eb7c8105d89f387", "headline": "Restored Tiles In the Heart Of Central Park", "keyword_org_rank_alt": 0.0, "headline_summary_senti": 0.0516, "summary_senti": -0.296, "headline_senti": 0.34, "trade_date": "2007-01-01", "lead_paragraph_senti": 0.7906, "pub_date": "2007-01-01T00:00:00Z", "keyword_in_summary": 0, "keyword_in_headline": 0}, "4fd366e88eb7c8105d8b6c46": {"_id": "4fd366e88eb7c8105d8b6c46", "headline": "Google in Talks to Buy Internet Ad Firm, Report Says", "keyword_org_rank_alt": 0.0, "headline_summary_senti": 0.3182, "summary_senti": 0.3182, "headline_senti": 0.0, "trade_date": "2007-01-22", "lead_paragraph_senti": 0.4019, "pub_date": "2007-01-22T07:49:33Z", "keyword_in_summary": 1, "keyword_in_headline": 1}, "548e28b738f0d8437a5db8e3": {"_id": "548e28b738f0d8437a5db8e3", "headline": "Profit Down, Outlook Up at Yahoo", "keyword_org_rank_alt": 0.5, "headline_summary_senti": 0.4404, "summary_senti": 0.0, "headline_senti": 0.4404, "trade_date": "2007-01-24", "lead_paragraph_senti": 0.0, "pub_date": "2007-01-24T00:00:00Z", "keyword_in_summary": 1, "keyword_in_headline": 0}, "548d6e2f38f0d80cddfa0982": {"_id": "548d6e2f38f0d80cddfa0982", "headline": "Google Acquires Stake in Chinese Web Site", "keyword_org_rank_alt": 1.0, "headline_summary_senti": 0.0, "summary_senti": 0.0, "headline_senti": 0.0, "trade_date": "2007-01-05", "lead_paragraph_senti": 0.0, "pub_date": "2007-01-05T00:00:00Z", "keyword_in_summary": 0, "keyword_in_headline": 1}, "4fd367278eb7c8105d8b72aa": {"_id": "4fd367278eb7c8105d8b72aa", "headline": "Amorous Brazilian Banker Wins Round With YouTube", "keyword_org_rank_alt": 0.0, "headline_summary_senti": 0.6765, "summary_senti": -0.2363, "headline_senti": 0.7579, "trade_date": "2007-01-05", "lead_paragraph_senti": -0.2363, "pub_date": "2007-01-05T11:50:06Z", "keyword_in_summary": 1, "keyword_in_headline": 0}, "4fd279cc8eb7c8105d83d801": {"_id": "4fd279cc8eb7c8105d83d801", "headline": "TODAY IN BUSINESS", "keyword_org_rank_alt": 0.0, "headline_summary_senti": 0.5106, "summary_senti": 0.5106, "headline_senti": 0.0, "trade_date": "2007-01-29", "lead_paragraph_senti": 0.9967, "pub_date": "2007-01-29T00:00:00Z", "keyword_in_summary": 0, "keyword_in_headline": 0}, "4fd2b0318eb7c8105d89f39b": {"_id": "4fd2b0318eb7c8105d89f39b", "headline": "News Summary", "keyword_org_rank_alt": 0.0, "headline_summary_senti": -0.6369, "summary_senti": -0.6369, "headline_senti": 0.0, "trade_date": "2007-01-03", "lead_paragraph_senti": -0.9979, "pub_date": "2007-01-03T00:00:00Z", "keyword_in_summary": 0, "keyword_in_headline": 0}, "548e758b38f0d8437a5dc034": {"_id": "548e758b38f0d8437a5dc034", "headline": "Google Posts Sharp Rise in Sales and Profits", "keyword_org_rank_alt": 0.0, "headline_summary_senti": 0.9144, "summary_senti": 0.8957, "headline_senti": 0.4404, "trade_date": "2007-01-31", "lead_paragraph_senti": 0.8957, "pub_date": "2007-01-31T00:00:00Z", "keyword_in_summary": 1, "keyword_in_headline": 1}}