[{"_id": "4fd39cb68eb7c8105d8dd0a7", "headline": "Android Beats iPhone With New Subscribers", "search_term_in_summary": 1, "search_term_in_headline": 0, "headline_summary_senti": 0.0, "summary_senti": 0.0, "headline_senti": 0.0, "trade_date": "2010-08-02", "lead_paragraph_senti": 0.5434, "pub_date": "2010-08-02T20:00:57Z"}, {"_id": "4fd39cab8eb7c8105d8dcf64", "headline": "Increasing Returns And Economic Areography", "search_term_in_summary": 0, "search_term_in_headline": 0, "headline_summary_senti": 0.0, "summary_senti": 0.0, "headline_senti": 0.0, "trade_date": "2010-08-02", "lead_paragraph_senti": 0.7717, "pub_date": "2010-08-02T18:20:10Z"}, {"_id": "5419229c38f0d86afc9a10c5", "headline": "Bing and Google in a Race for Features", "search_term_in_summary": 1, "search_term_in_headline": 1, "headline_summary_senti": 0.0, "summary_senti": 0.0, "headline_senti": 0.0, "trade_date": "2010-08-02", "lead_paragraph_senti": 0.0, "pub_date": "2010-08-02T00:00:00Z"}, {"_id": "4fd27f858eb7c8105d849f81", "headline": "Boldly Going At Google", "search_term_in_summary": 1, "search_term_in_headline": 1, "headline_summary_senti": 0.3612, "summary_senti": 0.0, "headline_senti": 0.3612, "trade_date": "2010-08-02", "lead_paragraph_senti": 0.7311, "pub_date": "2010-08-02T00:00:00Z"}, {"_id": "4fd39c418eb7c8105d8dbdf0", "headline": "Another Recession Casualty", "search_term_in_summary": 1, "search_term_in_headline": 0, "headline_summary_senti": -0.7783, "summary_senti": -0.1531, "headline_senti": -0.7351, "trade_date": "2010-08-03", "lead_paragraph_senti": -0.4215, "pub_date": "2010-08-03T17:49:47Z"}, {"_id": "4fd39c418eb7c8105d8dbe6c", "headline": "Can the 'Start-Up King' Sit Still?", "search_term_in_summary": 1, "search_term_in_headline": 0, "headline_summary_senti": 0.0, "summary_senti": 0.0, "headline_senti": 0.0, "trade_date": "2010-08-03", "lead_paragraph_senti": 0.0, "pub_date": "2010-08-03T06:17:24Z"}, {"_id": "4fd39c478eb7c8105d8dbf5b", "headline": "Google Kills Wave, Its Collaboration Tool", "search_term_in_summary": 1, "search_term_in_headline": 1, "headline_summary_senti": -0.6908, "summary_senti": -0.296, "headline_senti": -0.5423, "trade_date": "2010-08-04", "lead_paragraph_senti": 0.3628, "pub_date": "2010-08-04T18:58:52Z"}, {"_id": "4fd39cca8eb7c8105d8dd329", "headline": "Google Acquires Slide, Maker of Social Apps", "search_term_in_summary": 1, "search_term_in_headline": 1, "headline_summary_senti": 0.0, "summary_senti": 0.0, "headline_senti": 0.0, "trade_date": "2010-08-04", "lead_paragraph_senti": 0.0, "pub_date": "2010-08-04T18:15:14Z"}, {"_id": "4fd39c2c8eb7c8105d8dba4a", "headline": "Safari Extends Its Options", "search_term_in_summary": 0, "search_term_in_headline": 0, "headline_summary_senti": 0.128, "summary_senti": 0.0, "headline_senti": 0.128, "trade_date": "2010-08-04", "lead_paragraph_senti": 0.2732, "pub_date": "2010-08-04T17:09:37Z"}, {"_id": "4fd39cac8eb7c8105d8dcfad", "headline": "Google to Buy Levchin's Slide", "search_term_in_summary": 1, "search_term_in_headline": 1, "headline_summary_senti": 0.5574, "summary_senti": 0.5574, "headline_senti": 0.0, "trade_date": "2010-08-04", "lead_paragraph_senti": 0.0, "pub_date": "2010-08-04T17:08:10Z"}, {"_id": "54193fea38f0d86afc9a1366", "headline": "Google and Verizon Near Deal on Web Pay Tiers", "search_term_in_summary": 0, "search_term_in_headline": 1, "headline_summary_senti": 0.34, "summary_senti": 0.4215, "headline_senti": -0.1027, "trade_date": "2010-08-05", "lead_paragraph_senti": 0.4215, "pub_date": "2010-08-05T00:00:00Z"}, {"_id": "54193e4138f0d86afc9a1344", "headline": "Google Will Sell Brand Names as Keywords in Europe", "search_term_in_summary": 0, "search_term_in_headline": 1, "headline_summary_senti": 0.6486, "summary_senti": 0.6486, "headline_senti": 0.0, "trade_date": "2010-08-05", "lead_paragraph_senti": 0.6486, "pub_date": "2010-08-05T00:00:00Z"}, {"_id": "541948cd38f0d86afc9a142d", "headline": "F.C.C. Chief Opposes Fees for Internet Priority", "search_term_in_summary": 1, "search_term_in_headline": 0, "headline_summary_senti": 0.0, "summary_senti": 0.0, "headline_senti": 0.0, "trade_date": "2010-08-06", "lead_paragraph_senti": 0.0, "pub_date": "2010-08-06T00:00:00Z"}, {"_id": "4fd27f808eb7c8105d849aaf", "headline": "Corrections", "search_term_in_summary": 0, "search_term_in_headline": 0, "headline_summary_senti": 0.0, "summary_senti": 0.0, "headline_senti": 0.0, "trade_date": "2010-08-06", "lead_paragraph_senti": 0.0, "pub_date": "2010-08-06T00:00:00Z"}, {"_id": "5419560e38f0d86afc9a155b", "headline": "A Net Game for Google?", "search_term_in_summary": 1, "search_term_in_headline": 1, "headline_summary_senti": 0.2235, "summary_senti": 0.2235, "headline_senti": 0.0, "trade_date": "2010-08-08", "lead_paragraph_senti": 0.2235, "pub_date": "2010-08-08T00:00:00Z"}, {"_id": "4fd39cca8eb7c8105d8dd32d", "headline": "Google and Verizon Announce Net Neutrality Proposal", "search_term_in_summary": 1, "search_term_in_headline": 1, "headline_summary_senti": 0.0, "summary_senti": 0.0, "headline_senti": 0.0, "trade_date": "2010-08-09", "lead_paragraph_senti": 0.0, "pub_date": "2010-08-09T13:35:44Z"}, {"_id": "4fd39c418eb7c8105d8dbe1b", "headline": "Q.&A.: When Google Says No", "search_term_in_summary": 1, "search_term_in_headline": 1, "headline_summary_senti": -0.296, "summary_senti": 0.0, "headline_senti": -0.296, "trade_date": "2010-08-09", "lead_paragraph_senti": 0.0, "pub_date": "2010-08-09T07:00:40Z"}, {"_id": "4fd281d58eb7c8105d84e8b1", "headline": "Google Gives Up On Wave Service", "search_term_in_summary": 1, "search_term_in_headline": 1, "headline_summary_senti": -0.1531, "summary_senti": -0.1531, "headline_senti": 0.0, "trade_date": "2010-08-09", "lead_paragraph_senti": 0.155, "pub_date": "2010-08-09T00:00:00Z"}, {"_id": "4fd29aa58eb7c8105d87a2be", "headline": "Android Phones Outpace Apple's", "search_term_in_summary": 1, "search_term_in_headline": 0, "headline_summary_senti": 0.5118, "summary_senti": 0.5118, "headline_senti": 0.0, "trade_date": "2010-08-09", "lead_paragraph_senti": 0.7275, "pub_date": "2010-08-09T00:00:00Z"}, {"_id": "52489fd538f0d8198973ece2", "headline": "Net Neutrality", "search_term_in_summary": 1, "search_term_in_headline": 0, "headline_summary_senti": 0.0, "summary_senti": 0.0, "headline_senti": 0.0, "trade_date": "2010-08-10", "lead_paragraph_senti": 0.0, "pub_date": "2010-08-10T18:12:53Z"}, {"_id": "5419644938f0d86afc9a1699", "headline": "Web Plan From Google and Verizon Is Criticized", "search_term_in_summary": 0, "search_term_in_headline": 1, "headline_summary_senti": -0.5719, "summary_senti": -0.296, "headline_senti": -0.3612, "trade_date": "2010-08-10", "lead_paragraph_senti": -0.296, "pub_date": "2010-08-10T00:00:00Z"}, {"_id": "5419627f38f0d86afc9a1670", "headline": "Skype, Going Public, Hopes for $100 Million From First Offering", "search_term_in_summary": 1, "search_term_in_headline": 0, "headline_summary_senti": 0.4215, "summary_senti": 0.0, "headline_senti": 0.4215, "trade_date": "2010-08-10", "lead_paragraph_senti": 0.0, "pub_date": "2010-08-10T00:00:00Z"}, {"_id": "4fd39c478eb7c8105d8dbf56", "headline": "Tech Talk Podcast: Net Neutrality", "search_term_in_summary": 1, "search_term_in_headline": 0, "headline_summary_senti": 0.0, "summary_senti": 0.0, "headline_senti": 0.0, "trade_date": "2010-08-11", "lead_paragraph_senti": 0.1027, "pub_date": "2010-08-11T20:16:04Z"}, {"_id": "4fd39c598eb7c8105d8dc286", "headline": "Facebook Breaks With Google on Net Neutrality", "search_term_in_summary": 1, "search_term_in_headline": 1, "headline_summary_senti": -0.34, "summary_senti": -0.34, "headline_senti": 0.0, "trade_date": "2010-08-11", "lead_paragraph_senti": -0.3566, "pub_date": "2010-08-11T16:24:25Z"}, {"_id": "4fd39ca18eb7c8105d8dcd11", "headline": "New Android O.S. and Features", "search_term_in_summary": 1, "search_term_in_headline": 0, "headline_summary_senti": 0.3182, "summary_senti": 0.3182, "headline_senti": 0.0, "trade_date": "2010-08-12", "lead_paragraph_senti": -0.0129, "pub_date": "2010-08-12T19:23:05Z"}, {"_id": "4fd39cbe8eb7c8105d8dd201", "headline": "Android Beefs Up Hands-Free Commands", "search_term_in_summary": 1, "search_term_in_headline": 0, "headline_summary_senti": 0.0, "summary_senti": 0.0, "headline_senti": 0.0, "trade_date": "2010-08-12", "lead_paragraph_senti": 0.0, "pub_date": "2010-08-12T16:26:48Z"}, {"_id": "4fd39ca18eb7c8105d8dcc9d", "headline": "More on the Net Neutrality Debate", "search_term_in_summary": 0, "search_term_in_headline": 0, "headline_summary_senti": 0.0, "summary_senti": 0.0, "headline_senti": 0.0, "trade_date": "2010-08-12", "lead_paragraph_senti": 0.1027, "pub_date": "2010-08-12T13:19:15Z"}, {"_id": "4fd39c8a8eb7c8105d8dc9c6", "headline": "Prisoners of White Guilt", "search_term_in_summary": 1, "search_term_in_headline": 0, "headline_summary_senti": -0.7506, "summary_senti": -0.25, "headline_senti": -0.6597, "trade_date": "2010-08-12", "lead_paragraph_senti": -0.4939, "pub_date": "2010-08-12T06:27:15Z"}, {"_id": "5419790938f0d86afc9a188c", "headline": "Web Plan Is Dividing Companies", "search_term_in_summary": 1, "search_term_in_headline": 0, "headline_summary_senti": -0.3089, "summary_senti": -0.3089, "headline_senti": 0.0, "trade_date": "2010-08-12", "lead_paragraph_senti": -0.3089, "pub_date": "2010-08-12T00:00:00Z"}, {"_id": "541973ed38f0d86afc9a180d", "headline": "D.I.Y. Tool for Apps Needs Work", "search_term_in_summary": 1, "search_term_in_headline": 0, "headline_summary_senti": 0.5859, "summary_senti": 0.5859, "headline_senti": 0.0, "trade_date": "2010-08-12", "lead_paragraph_senti": 0.5859, "pub_date": "2010-08-12T00:00:00Z"}, {"_id": "54198ed838f0d86afc9a1a89", "headline": "The Google/Verizon Payment Plan", "search_term_in_summary": 1, "search_term_in_headline": 1, "headline_summary_senti": -0.6124, "summary_senti": -0.6124, "headline_senti": 0.0, "trade_date": "2010-08-14", "lead_paragraph_senti": -0.5927, "pub_date": "2010-08-14T00:00:00Z"}, {"_id": "54194f2138f0d86afc9a14c7", "headline": "Google Leads, You Pedal", "search_term_in_summary": 1, "search_term_in_headline": 1, "headline_summary_senti": 0.34, "summary_senti": 0.34, "headline_senti": 0.0, "trade_date": "2010-08-15", "lead_paragraph_senti": 0.34, "pub_date": "2010-08-15T00:00:00Z"}, {"_id": "4fd2a84d8eb7c8105d8928ff", "headline": "SWEAT; 1! (Stroke) 2! (Stroke) Sit Up! Stop Chatting!", "search_term_in_summary": 0, "search_term_in_headline": 0, "headline_summary_senti": 0.4885, "summary_senti": 0.4939, "headline_senti": -0.5216, "trade_date": "2010-08-15", "lead_paragraph_senti": 0.0935, "pub_date": "2010-08-15T00:00:00Z"}, {"_id": "4fd39c5a8eb7c8105d8dc2d2", "headline": "Q.&A.: Color-Coded Traffic in Google Maps", "search_term_in_summary": 1, "search_term_in_headline": 1, "headline_summary_senti": 0.0, "summary_senti": 0.0, "headline_senti": 0.0, "trade_date": "2010-08-16", "lead_paragraph_senti": 0.0, "pub_date": "2010-08-16T07:00:41Z"}, {"_id": "4fd39ca28eb7c8105d8dcdc5", "headline": "'Super Angel' Senkut Raises $40 Million Fund", "search_term_in_summary": 1, "search_term_in_headline": 0, "headline_summary_senti": 0.7096, "summary_senti": 0.25, "headline_senti": 0.5994, "trade_date": "2010-08-16", "lead_paragraph_senti": 0.25, "pub_date": "2010-08-16T04:36:56Z"}, {"_id": "4fd39c198eb7c8105d8db7c9", "headline": "Google Deal for Like.Com Is Said to Be Near", "search_term_in_summary": 1, "search_term_in_headline": 1, "headline_summary_senti": 0.0, "summary_senti": 0.0, "headline_senti": 0.0, "trade_date": "2010-08-16", "lead_paragraph_senti": 0.0, "pub_date": "2010-08-16T04:30:31Z"}, {"_id": "541996b838f0d86afc9a1b45", "headline": "Variable Pricing and Net Neutrality", "search_term_in_summary": 1, "search_term_in_headline": 0, "headline_summary_senti": 0.7783, "summary_senti": 0.7783, "headline_senti": 0.0, "trade_date": "2010-08-16", "lead_paragraph_senti": 0.7783, "pub_date": "2010-08-16T00:00:00Z"}, {"_id": "541996fd38f0d86afc9a1b4c", "headline": "Google Plan With Verizon Disillusions Some Allies", "search_term_in_summary": 1, "search_term_in_headline": 1, "headline_summary_senti": -0.5267, "summary_senti": -0.2023, "headline_senti": -0.3818, "trade_date": "2010-08-16", "lead_paragraph_senti": 0.0, "pub_date": "2010-08-16T00:00:00Z"}, {"_id": "541996d838f0d86afc9a1b48", "headline": "Internet Proposal From Google and Verizon Raises Fears for Privacy", "search_term_in_summary": 0, "search_term_in_headline": 1, "headline_summary_senti": 0.4188, "summary_senti": 0.6794, "headline_senti": -0.4215, "trade_date": "2010-08-16", "lead_paragraph_senti": 0.6794, "pub_date": "2010-08-16T00:00:00Z"}, {"_id": "4fd27f868eb7c8105d84a079", "headline": "Better Voice Commands For Android Phones", "search_term_in_summary": 1, "search_term_in_headline": 0, "headline_summary_senti": 0.4404, "summary_senti": 0.0, "headline_senti": 0.4404, "trade_date": "2010-08-16", "lead_paragraph_senti": 0.0, "pub_date": "2010-08-16T00:00:00Z"}, {"_id": "5419a73b38f0d86afc9a1ccd", "headline": "Google Sued in Spain Over Data Collecting", "search_term_in_summary": 1, "search_term_in_headline": 1, "headline_summary_senti": -0.5994, "summary_senti": -0.5994, "headline_senti": 0.0, "trade_date": "2010-08-18", "lead_paragraph_senti": -0.5994, "pub_date": "2010-08-18T00:00:00Z"}, {"_id": "4fd39c4d8eb7c8105d8dc1c1", "headline": "Facebook Introduces a Location-Based Service", "search_term_in_summary": 1, "search_term_in_headline": 0, "headline_summary_senti": 0.4019, "summary_senti": 0.4019, "headline_senti": 0.0, "trade_date": "2010-08-19", "lead_paragraph_senti": 0.4019, "pub_date": "2010-08-19T03:16:42Z"}, {"_id": "4fd39c908eb7c8105d8dcb63", "headline": "No Safe Harbors in Argentina", "search_term_in_summary": 0, "search_term_in_headline": 0, "headline_summary_senti": -0.0258, "summary_senti": -0.2023, "headline_senti": 0.1779, "trade_date": "2010-08-20", "lead_paragraph_senti": 0.6597, "pub_date": "2010-08-20T18:40:28Z"}, {"_id": "5419bf3638f0d80959e6b9ec", "headline": "Google and Yahoo Win Appeal in Argentine Case", "search_term_in_summary": 0, "search_term_in_headline": 1, "headline_summary_senti": 0.4404, "summary_senti": -0.2263, "headline_senti": 0.5859, "trade_date": "2010-08-20", "lead_paragraph_senti": -0.2263, "pub_date": "2010-08-20T00:00:00Z"}, {"_id": "5419c5db38f0d80959e6ba89", "headline": "Net Neutrality", "search_term_in_summary": 1, "search_term_in_headline": 0, "headline_summary_senti": 0.0, "summary_senti": 0.0, "headline_senti": 0.0, "trade_date": "2010-08-22", "lead_paragraph_senti": 0.0, "pub_date": "2010-08-22T00:00:00Z"}, {"_id": "4fd39c198eb7c8105d8db7d2", "headline": "Casting a Feel-Good Google Movie", "search_term_in_summary": 1, "search_term_in_headline": 1, "headline_summary_senti": 0.5106, "summary_senti": 0.5106, "headline_senti": 0.0, "trade_date": "2010-08-23", "lead_paragraph_senti": 0.5106, "pub_date": "2010-08-23T04:23:12Z"}, {"_id": "4fd39c8b8eb7c8105d8dca2e", "headline": "How to Make Phone Calls From Inside Gmail", "search_term_in_summary": 0, "search_term_in_headline": 0, "headline_summary_senti": 0.0, "summary_senti": 0.0, "headline_senti": 0.0, "trade_date": "2010-08-25", "lead_paragraph_senti": 0.6124, "pub_date": "2010-08-25T16:43:14Z"}, {"_id": "4fd39ca18eb7c8105d8dcc9c", "headline": "Google Gives Real-Time Search Its Own Page", "search_term_in_summary": 1, "search_term_in_headline": 1, "headline_summary_senti": 0.5106, "summary_senti": 0.5106, "headline_senti": 0.0, "trade_date": "2010-08-26", "lead_paragraph_senti": 0.0, "pub_date": "2010-08-26T14:21:28Z"}, {"_id": "4fd39cab8eb7c8105d8dcf55", "headline": "Pogue's Posts: Google Shakes It Up Again", "search_term_in_summary": 1, "search_term_in_headline": 1, "headline_summary_senti": 0.6224, "summary_senti": 0.6224, "headline_senti": 0.0, "trade_date": "2010-08-26", "lead_paragraph_senti": 0.0, "pub_date": "2010-08-26T14:01:15Z"}, {"_id": "4fd39c3c8eb7c8105d8dbd01", "headline": "Google Shakes It Up Again With Free Phone Calls", "search_term_in_summary": 1, "search_term_in_headline": 1, "headline_summary_senti": 0.8116, "summary_senti": 0.6224, "headline_senti": 0.5106, "trade_date": "2010-08-26", "lead_paragraph_senti": 0.7184, "pub_date": "2010-08-26T13:37:43Z"}, {"_id": "4fd39c7d8eb7c8105d8dc770", "headline": "Four Useful Google Docs Tricks", "search_term_in_summary": 1, "search_term_in_headline": 1, "headline_summary_senti": 0.6908, "summary_senti": 0.5106, "headline_senti": 0.34, "trade_date": "2010-08-26", "lead_paragraph_senti": 0.8934, "pub_date": "2010-08-26T11:03:49Z"}, {"_id": "5419ee2938f0d80959e6be38", "headline": "Google Is Offering Phone Calls via Gmail", "search_term_in_summary": 1, "search_term_in_headline": 1, "headline_summary_senti": 0.0, "summary_senti": 0.0, "headline_senti": 0.0, "trade_date": "2010-08-26", "lead_paragraph_senti": 0.0, "pub_date": "2010-08-26T00:00:00Z"}, {"_id": "4fd39cab8eb7c8105d8dcf14", "headline": "Government Takes Closer Look at Google's ITA Acquisition", "search_term_in_summary": 1, "search_term_in_headline": 1, "headline_summary_senti": 0.5267, "summary_senti": 0.5267, "headline_senti": 0.0, "trade_date": "2010-08-27", "lead_paragraph_senti": 0.5267, "pub_date": "2010-08-27T17:24:22Z"}, {"_id": "4fd39c8b8eb7c8105d8dc9d5", "headline": "Google Acquires Angstro, a Social Networking Start-Up", "search_term_in_summary": 1, "search_term_in_headline": 1, "headline_summary_senti": 0.0, "summary_senti": 0.0, "headline_senti": 0.0, "trade_date": "2010-08-27", "lead_paragraph_senti": 0.3182, "pub_date": "2010-08-27T16:45:09Z"}, {"_id": "4fd39c4c8eb7c8105d8dc145", "headline": "Six Things Google's Free Phone Service Can't Do (and One It Does Very Well)", "search_term_in_summary": 1, "search_term_in_headline": 1, "headline_summary_senti": 0.765, "summary_senti": 0.5106, "headline_senti": 0.5106, "trade_date": "2010-08-27", "lead_paragraph_senti": 0.0, "pub_date": "2010-08-27T13:38:10Z"}, {"_id": "4fd39cab8eb7c8105d8dcf15", "headline": "Google Offers Respite From Inbox Overload", "search_term_in_summary": 1, "search_term_in_headline": 1, "headline_summary_senti": 0.7506, "summary_senti": 0.836, "headline_senti": -0.3612, "trade_date": "2010-08-31", "lead_paragraph_senti": -0.4515, "pub_date": "2010-08-30T23:40:49Z"}, {"_id": "4fd39c8b8eb7c8105d8dc9d6", "headline": "Microsoft Enters Google's Unwalled Garden", "search_term_in_summary": 1, "search_term_in_headline": 1, "headline_summary_senti": 0.0, "summary_senti": 0.0, "headline_senti": 0.0, "trade_date": "2010-08-30", "lead_paragraph_senti": -0.1779, "pub_date": "2010-08-30T18:23:46Z"}, {"_id": "4fd39c5a8eb7c8105d8dc2d4", "headline": "Does Google's Free Phone Service Work in Other Countries?", "search_term_in_summary": 1, "search_term_in_headline": 1, "headline_summary_senti": 0.5106, "summary_senti": 0.2846, "headline_senti": 0.5106, "trade_date": "2010-08-30", "lead_paragraph_senti": 0.9403, "pub_date": "2010-08-30T17:46:12Z"}, {"_id": "4fd39c2c8eb7c8105d8dba16", "headline": "A Video Show From Google Highlights Hot Topics", "search_term_in_summary": 1, "search_term_in_headline": 1, "headline_summary_senti": 0.0, "summary_senti": 0.0, "headline_senti": 0.0, "trade_date": "2010-08-30", "lead_paragraph_senti": 0.5994, "pub_date": "2010-08-30T12:43:02Z"}, {"_id": "4fd39ca28eb7c8105d8dcdeb", "headline": "The Google Deal Machine", "search_term_in_summary": 1, "search_term_in_headline": 1, "headline_summary_senti": 0.0, "summary_senti": 0.0, "headline_senti": 0.0, "trade_date": "2010-08-30", "lead_paragraph_senti": 0.0, "pub_date": "2010-08-30T10:10:50Z"}, {"_id": "4fd39ca28eb7c8105d8dcde6", "headline": "Google Acquires Angstro, a Social Networking Aid", "search_term_in_summary": 1, "search_term_in_headline": 1, "headline_summary_senti": 0.3612, "summary_senti": 0.3612, "headline_senti": 0.0, "trade_date": "2010-08-30", "lead_paragraph_senti": 0.3612, "pub_date": "2010-08-30T05:40:01Z"}, {"_id": "541a0f1938f0d80959e6c157", "headline": "Software War Pits Oracle vs. Google", "search_term_in_summary": 0, "search_term_in_headline": 1, "headline_summary_senti": -0.7269, "summary_senti": -0.296, "headline_senti": -0.5994, "trade_date": "2010-08-30", "lead_paragraph_senti": -0.5267, "pub_date": "2010-08-30T00:00:00Z"}, {"_id": "4fd2b73c8eb7c8105d8abf65", "headline": "Real-Time Search Comes to Google", "search_term_in_summary": 1, "search_term_in_headline": 1, "headline_summary_senti": 0.0, "summary_senti": 0.0, "headline_senti": 0.0, "trade_date": "2010-08-30", "lead_paragraph_senti": 0.3612, "pub_date": "2010-08-30T00:00:00Z"}, {"_id": "4fd2b72f8eb7c8105d8ab854", "headline": "Seeing That Ad on Every Site? You're Right. It's Tracking You.", "search_term_in_summary": 1, "search_term_in_headline": 0, "headline_summary_senti": -0.2732, "summary_senti": -0.2732, "headline_senti": 0.0, "trade_date": "2010-08-30", "lead_paragraph_senti": 0.358, "pub_date": "2010-08-30T00:00:00Z"}, {"_id": "4fd39c5a8eb7c8105d8dc2d5", "headline": "How to Train Google's E-mail Triage System", "search_term_in_summary": 1, "search_term_in_headline": 1, "headline_summary_senti": -0.128, "summary_senti": -0.128, "headline_senti": 0.0, "trade_date": "2010-08-31", "lead_paragraph_senti": -0.4019, "pub_date": "2010-08-31T19:28:56Z"}, {"_id": "4fd39c7e8eb7c8105d8dc86b", "headline": "Google Buys Mobile Networker SocialDeck", "search_term_in_summary": 1, "search_term_in_headline": 1, "headline_summary_senti": 0.0772, "summary_senti": 0.0772, "headline_senti": 0.0, "trade_date": "2010-08-31", "lead_paragraph_senti": 0.0772, "pub_date": "2010-08-31T02:55:54Z"}]