[{"summary_senti": {"neg": 0.138, "neu": 0.776, "pos": 0.085, "compound": -0.0941}, "headline": "German Regulator Warns Google Over Collecting Users' Data", "search_term_in_summary": 0, "search_term_in_headline": 1, "headline_summary_senti": {"neg": 0.145, "neu": 0.79, "pos": 0.064, "compound": -0.194}, "headline_senti": {"neg": 0.167, "neu": 0.833, "pos": 0.0, "compound": -0.1027}, "trade_date": "2014-10-01", "lead_paragraph_senti": {"neg": 0.0, "neu": 1.0, "pos": 0.0, "compound": 0.0}, "pub_date": "2014-10-01T07:03:03Z"}, {"summary_senti": {"neg": 0.0, "neu": 0.83, "pos": 0.17, "compound": 0.5719}, "headline": "Drones vs. Kidneys: Google Autofill on the Economy", "search_term_in_summary": 1, "search_term_in_headline": 1, "headline_summary_senti": {"neg": 0.0, "neu": 0.868, "pos": 0.132, "compound": 0.5719}, "headline_senti": {"neg": 0.0, "neu": 1.0, "pos": 0.0, "compound": 0.0}, "trade_date": "2014-10-02", "lead_paragraph_senti": {"neg": 0.0, "neu": 1.0, "pos": 0.0, "compound": 0.0}, "pub_date": "2014-10-02T11:08:30Z"}, {"summary_senti": {"neg": 0.0, "neu": 0.794, "pos": 0.206, "compound": 0.6908}, "headline": "Antitrust Nominee in Europe Promises Scrutiny of Big Tech Companies", "search_term_in_summary": 1, "search_term_in_headline": 0, "headline_summary_senti": {"neg": 0.0, "neu": 0.789, "pos": 0.211, "compound": 0.8074}, "headline_senti": {"neg": 0.0, "neu": 0.776, "pos": 0.224, "compound": 0.3818}, "trade_date": "2014-10-03", "lead_paragraph_senti": {"neg": 0.0, "neu": 1.0, "pos": 0.0, "compound": 0.0}, "pub_date": "2014-10-03T04:20:13Z"}, {"summary_senti": {"neg": 0.0, "neu": 0.967, "pos": 0.033, "compound": 0.2263}, "headline": "Times Articles Removed From Google Results in Europe", "search_term_in_summary": 1, "search_term_in_headline": 1, "headline_summary_senti": {"neg": 0.0, "neu": 0.971, "pos": 0.029, "compound": 0.2263}, "headline_senti": {"neg": 0.0, "neu": 1.0, "pos": 0.0, "compound": 0.0}, "trade_date": "2014-10-04", "lead_paragraph_senti": {"neg": 0.0, "neu": 0.917, "pos": 0.083, "compound": 0.2263}, "pub_date": "2014-10-04T00:00:00Z"}, {"summary_senti": {"neg": 0.0, "neu": 0.693, "pos": 0.307, "compound": 0.9059}, "headline": "Silicon Valley&#8217;s Diversity Problem", "search_term_in_summary": 1, "search_term_in_headline": 0, "headline_summary_senti": {"neg": 0.055, "neu": 0.674, "pos": 0.271, "compound": 0.862}, "headline_senti": {"neg": 0.474, "neu": 0.526, "pos": 0.0, "compound": -0.4019}, "trade_date": "2014-10-05", "lead_paragraph_senti": {"neg": 0.0, "neu": 0.838, "pos": 0.162, "compound": 0.4404}, "pub_date": "2014-10-05T00:00:00Z"}, {"summary_senti": {"neg": 0.11, "neu": 0.89, "pos": 0.0, "compound": -0.7003}, "headline": "Daily Report: From Lemonade Stand to Twitter\u2019s I.P.O., a 10-Year-Old\u2019s Journey to Silicon Valley", "search_term_in_summary": 1, "search_term_in_headline": 0, "headline_summary_senti": {"neg": 0.085, "neu": 0.915, "pos": 0.0, "compound": -0.7003}, "headline_senti": {"neg": 0.0, "neu": 1.0, "pos": 0.0, "compound": 0.0}, "trade_date": "2014-10-08", "lead_paragraph_senti": {"neg": 0.0, "neu": 1.0, "pos": 0.0, "compound": 0.0}, "pub_date": "2014-10-08T08:09:42Z"}, {"summary_senti": {"neg": 0.0, "neu": 1.0, "pos": 0.0, "compound": 0.0}, "headline": "Google Provides Details on 'Right to Be Forgotten' Requests in E.U.", "search_term_in_summary": 1, "search_term_in_headline": 1, "headline_summary_senti": {"neg": 0.054, "neu": 0.946, "pos": 0.0, "compound": -0.2263}, "headline_senti": {"neg": 0.16, "neu": 0.84, "pos": 0.0, "compound": -0.2263}, "trade_date": "2014-10-09", "lead_paragraph_senti": {"neg": 0.0, "neu": 1.0, "pos": 0.0, "compound": 0.0}, "pub_date": "2014-10-09T19:00:02Z"}, {"summary_senti": {"neg": 0.0, "neu": 0.738, "pos": 0.262, "compound": 0.8357}, "headline": "Technology Titans Lead Ranking of Most Valuable Brands ", "search_term_in_summary": 1, "search_term_in_headline": 0, "headline_summary_senti": {"neg": 0.0, "neu": 0.723, "pos": 0.277, "compound": 0.9059}, "headline_senti": {"neg": 0.0, "neu": 0.674, "pos": 0.326, "compound": 0.5256}, "trade_date": "2014-10-09", "lead_paragraph_senti": {"neg": 0.0, "neu": 0.714, "pos": 0.286, "compound": 0.7184}, "pub_date": "2014-10-09T00:00:00Z"}, {"summary_senti": {"neg": 0.0, "neu": 0.903, "pos": 0.097, "compound": 0.4215}, "headline": "Recording Live Audio Streams in Windows", "search_term_in_summary": 1, "search_term_in_headline": 0, "headline_summary_senti": {"neg": 0.0, "neu": 0.92, "pos": 0.08, "compound": 0.4215}, "headline_senti": {"neg": 0.0, "neu": 1.0, "pos": 0.0, "compound": 0.0}, "trade_date": "2014-10-09", "lead_paragraph_senti": {"neg": 0.0, "neu": 0.722, "pos": 0.278, "compound": 0.4019}, "pub_date": "2014-10-09T00:00:00Z"}, {"summary_senti": {"neg": 0.0, "neu": 1.0, "pos": 0.0, "compound": 0.0}, "headline": "Moving a Music Library to Linux", "search_term_in_summary": 1, "search_term_in_headline": 0, "headline_summary_senti": {"neg": 0.0, "neu": 1.0, "pos": 0.0, "compound": 0.0}, "headline_senti": {"neg": 0.0, "neu": 1.0, "pos": 0.0, "compound": 0.0}, "trade_date": "2014-10-10", "lead_paragraph_senti": {"neg": 0.0, "neu": 1.0, "pos": 0.0, "compound": 0.0}, "pub_date": "2014-10-10T00:00:00Z"}, {"summary_senti": {"neg": 0.129, "neu": 0.742, "pos": 0.129, "compound": -0.0}, "headline": "iPhones, iPads and the Search Query Gap", "search_term_in_summary": 1, "search_term_in_headline": 0, "headline_summary_senti": {"neg": 0.108, "neu": 0.783, "pos": 0.108, "compound": -0.0}, "headline_senti": {"neg": 0.0, "neu": 1.0, "pos": 0.0, "compound": 0.0}, "trade_date": "2014-10-10", "lead_paragraph_senti": {"neg": 0.0, "neu": 1.0, "pos": 0.0, "compound": 0.0}, "pub_date": "2014-10-10T07:30:49Z"}, {"summary_senti": {"neg": 0.209, "neu": 0.791, "pos": 0.0, "compound": -0.2755}, "headline": "Why Germans Are Afraid of Google", "search_term_in_summary": 0, "search_term_in_headline": 1, "headline_summary_senti": {"neg": 0.131, "neu": 0.869, "pos": 0.0, "compound": -0.2755}, "headline_senti": {"neg": 0.0, "neu": 1.0, "pos": 0.0, "compound": 0.0}, "trade_date": "2014-10-11", "lead_paragraph_senti": {"neg": 0.209, "neu": 0.791, "pos": 0.0, "compound": -0.2755}, "pub_date": "2014-10-11T12:30:00Z"}, {"summary_senti": {"neg": 0.0, "neu": 0.762, "pos": 0.238, "compound": 0.3612}, "headline": "Why Germans Are Afraid of Google", "search_term_in_summary": 0, "search_term_in_headline": 1, "headline_summary_senti": {"neg": 0.0, "neu": 0.848, "pos": 0.152, "compound": 0.3612}, "headline_senti": {"neg": 0.0, "neu": 1.0, "pos": 0.0, "compound": 0.0}, "trade_date": "2014-10-12", "lead_paragraph_senti": {"neg": 0.0, "neu": 0.762, "pos": 0.238, "compound": 0.3612}, "pub_date": "2014-10-12T00:00:00Z"}, {"summary_senti": {"neg": 0.0, "neu": 0.81, "pos": 0.19, "compound": 0.7906}, "headline": "Hands Off or Hands On, Tech-Heavy Funds Led the Pack", "search_term_in_summary": 1, "search_term_in_headline": 0, "headline_summary_senti": {"neg": 0.0, "neu": 0.846, "pos": 0.154, "compound": 0.7906}, "headline_senti": {"neg": 0.0, "neu": 1.0, "pos": 0.0, "compound": 0.0}, "trade_date": "2014-10-12", "lead_paragraph_senti": {"neg": 0.0, "neu": 0.887, "pos": 0.113, "compound": 0.4201}, "pub_date": "2014-10-12T00:00:00Z"}, {"summary_senti": {"neg": 0.0, "neu": 1.0, "pos": 0.0, "compound": 0.0}, "headline": "Am I Sick? Google Has a Doctor Waiting on Video", "search_term_in_summary": 1, "search_term_in_headline": 1, "headline_summary_senti": {"neg": 0.125, "neu": 0.875, "pos": 0.0, "compound": -0.5106}, "headline_senti": {"neg": 0.32, "neu": 0.68, "pos": 0.0, "compound": -0.5106}, "trade_date": "2014-10-13", "lead_paragraph_senti": {"neg": 0.0, "neu": 1.0, "pos": 0.0, "compound": 0.0}, "pub_date": "2014-10-13T17:37:00Z"}, {"summary_senti": {"neg": 0.0, "neu": 0.883, "pos": 0.117, "compound": 0.5106}, "headline": "Google Executive Chairman: Amazon Is a Lovely Place to Shop and Search ", "search_term_in_summary": 1, "search_term_in_headline": 1, "headline_summary_senti": {"neg": 0.0, "neu": 0.794, "pos": 0.206, "compound": 0.8316}, "headline_senti": {"neg": 0.0, "neu": 0.621, "pos": 0.379, "compound": 0.6705}, "trade_date": "2014-10-14", "lead_paragraph_senti": {"neg": 0.0, "neu": 1.0, "pos": 0.0, "compound": 0.0}, "pub_date": "2014-10-14T16:38:12Z"}, {"summary_senti": {"neg": 0.07, "neu": 0.87, "pos": 0.06, "compound": -0.1027}, "headline": "Ireland to Phase Out &#8216;Double Irish&#8217; Tax Break Used by Tech Giants", "search_term_in_summary": 1, "search_term_in_headline": 0, "headline_summary_senti": {"neg": 0.054, "neu": 0.899, "pos": 0.047, "compound": -0.1027}, "headline_senti": {"neg": 0.0, "neu": 1.0, "pos": 0.0, "compound": 0.0}, "trade_date": "2014-10-15", "lead_paragraph_senti": {"neg": 0.0, "neu": 0.902, "pos": 0.098, "compound": 0.3612}, "pub_date": "2014-10-15T00:00:00Z"}, {"summary_senti": {"neg": 0.158, "neu": 0.842, "pos": 0.0, "compound": -0.4588}, "headline": "Stephen Colbert and the Angry Inch", "search_term_in_summary": 1, "search_term_in_headline": 0, "headline_summary_senti": {"neg": 0.231, "neu": 0.769, "pos": 0.0, "compound": -0.743}, "headline_senti": {"neg": 0.398, "neu": 0.602, "pos": 0.0, "compound": -0.5106}, "trade_date": "2014-10-16", "lead_paragraph_senti": {"neg": 0.0, "neu": 1.0, "pos": 0.0, "compound": 0.0}, "pub_date": "2014-10-16T11:44:52Z"}, {"summary_senti": {"neg": 0.098, "neu": 0.838, "pos": 0.063, "compound": -0.1779}, "headline": "Google Profit Will Depend on Wringing More From Mobile Ads", "search_term_in_summary": 1, "search_term_in_headline": 1, "headline_summary_senti": {"neg": 0.079, "neu": 0.822, "pos": 0.099, "compound": 0.296}, "headline_senti": {"neg": 0.0, "neu": 0.756, "pos": 0.244, "compound": 0.4404}, "trade_date": "2014-10-16", "lead_paragraph_senti": {"neg": 0.0, "neu": 0.813, "pos": 0.187, "compound": 0.6486}, "pub_date": "2014-10-16T00:00:00Z"}, {"summary_senti": {"neg": 0.0, "neu": 0.785, "pos": 0.215, "compound": 0.6369}, "headline": "Daily Report: Analysts Wonder About Google's Next Phase", "search_term_in_summary": 1, "search_term_in_headline": 1, "headline_summary_senti": {"neg": 0.0, "neu": 0.839, "pos": 0.161, "compound": 0.6369}, "headline_senti": {"neg": 0.0, "neu": 1.0, "pos": 0.0, "compound": 0.0}, "trade_date": "2014-10-17", "lead_paragraph_senti": {"neg": 0.0, "neu": 1.0, "pos": 0.0, "compound": 0.0}, "pub_date": "2014-10-17T07:39:29Z"}, {"summary_senti": {"neg": 0.0, "neu": 0.824, "pos": 0.176, "compound": 0.8658}, "headline": "Analysts Ask What\u2019s Next for Google", "search_term_in_summary": 1, "search_term_in_headline": 1, "headline_summary_senti": {"neg": 0.0, "neu": 0.84, "pos": 0.16, "compound": 0.8658}, "headline_senti": {"neg": 0.0, "neu": 1.0, "pos": 0.0, "compound": 0.0}, "trade_date": "2014-10-17", "lead_paragraph_senti": {"neg": 0.0, "neu": 0.785, "pos": 0.215, "compound": 0.6369}, "pub_date": "2014-10-17T00:00:00Z"}, {"summary_senti": {"neg": 0.0, "neu": 1.0, "pos": 0.0, "compound": 0.0}, "headline": "James Comey, F.B.I. Director, Hints at Action as Cellphone Data Is Locked", "search_term_in_summary": 1, "search_term_in_headline": 0, "headline_summary_senti": {"neg": 0.0, "neu": 1.0, "pos": 0.0, "compound": 0.0}, "headline_senti": {"neg": 0.0, "neu": 1.0, "pos": 0.0, "compound": 0.0}, "trade_date": "2014-10-17", "lead_paragraph_senti": {"neg": 0.0, "neu": 1.0, "pos": 0.0, "compound": 0.0}, "pub_date": "2014-10-17T00:00:00Z"}, {"summary_senti": {"neg": 0.182, "neu": 0.772, "pos": 0.046, "compound": -0.5994}, "headline": "Stephen Colbert Has a Mock Feud With Google Over Search Results", "search_term_in_summary": 1, "search_term_in_headline": 1, "headline_summary_senti": {"neg": 0.249, "neu": 0.719, "pos": 0.031, "compound": -0.8442}, "headline_senti": {"neg": 0.394, "neu": 0.606, "pos": 0.0, "compound": -0.6369}, "trade_date": "2014-10-20", "lead_paragraph_senti": {"neg": 0.122, "neu": 0.827, "pos": 0.051, "compound": -0.4215}, "pub_date": "2014-10-20T00:00:00Z"}, {"summary_senti": {"neg": 0.0, "neu": 0.912, "pos": 0.088, "compound": 0.34}, "headline": "Google Invests Heavily in Magic Leap's Effort to Blend Illusion and Reality", "search_term_in_summary": 1, "search_term_in_headline": 1, "headline_summary_senti": {"neg": 0.0, "neu": 0.939, "pos": 0.061, "compound": 0.34}, "headline_senti": {"neg": 0.0, "neu": 1.0, "pos": 0.0, "compound": 0.0}, "trade_date": "2014-10-21", "lead_paragraph_senti": {"neg": 0.0, "neu": 1.0, "pos": 0.0, "compound": 0.0}, "pub_date": "2014-10-21T16:09:57Z"}, {"summary_senti": {"neg": 0.0, "neu": 0.913, "pos": 0.087, "compound": 0.2023}, "headline": "Daily Report: Chasing Marty McFly's Hoverboard", "search_term_in_summary": 1, "search_term_in_headline": 0, "headline_summary_senti": {"neg": 0.0, "neu": 0.933, "pos": 0.067, "compound": 0.2023}, "headline_senti": {"neg": 0.0, "neu": 1.0, "pos": 0.0, "compound": 0.0}, "trade_date": "2014-10-21", "lead_paragraph_senti": {"neg": 0.0, "neu": 1.0, "pos": 0.0, "compound": 0.0}, "pub_date": "2014-10-21T06:29:02Z"}, {"summary_senti": {"neg": 0.0, "neu": 0.941, "pos": 0.059, "compound": 0.1779}, "headline": "For Microsoft, Cloud Business Looks More Promising Than Mobile ", "search_term_in_summary": 1, "search_term_in_headline": 0, "headline_summary_senti": {"neg": 0.0, "neu": 0.882, "pos": 0.118, "compound": 0.5709}, "headline_senti": {"neg": 0.0, "neu": 0.728, "pos": 0.272, "compound": 0.4576}, "trade_date": "2014-10-21", "lead_paragraph_senti": {"neg": 0.0, "neu": 1.0, "pos": 0.0, "compound": 0.0}, "pub_date": "2014-10-21T00:51:22Z"}, {"summary_senti": {"neg": 0.059, "neu": 0.821, "pos": 0.12, "compound": 0.4417}, "headline": "Hoverboard? Still in the Future", "search_term_in_summary": 1, "search_term_in_headline": 0, "headline_summary_senti": {"neg": 0.053, "neu": 0.838, "pos": 0.109, "compound": 0.4417}, "headline_senti": {"neg": 0.0, "neu": 1.0, "pos": 0.0, "compound": 0.0}, "trade_date": "2014-10-21", "lead_paragraph_senti": {"neg": 0.0, "neu": 0.884, "pos": 0.116, "compound": 0.3612}, "pub_date": "2014-10-21T00:00:00Z"}, {"summary_senti": {"neg": 0.0, "neu": 0.846, "pos": 0.154, "compound": 0.25}, "headline": "Google Wants Inbox to Be Your Email System for the Next Decade", "search_term_in_summary": 1, "search_term_in_headline": 1, "headline_summary_senti": {"neg": 0.0, "neu": 0.92, "pos": 0.08, "compound": 0.25}, "headline_senti": {"neg": 0.0, "neu": 1.0, "pos": 0.0, "compound": 0.0}, "trade_date": "2014-10-22", "lead_paragraph_senti": {"neg": 0.0, "neu": 1.0, "pos": 0.0, "compound": 0.0}, "pub_date": "2014-10-22T13:00:29Z"}, {"summary_senti": {"neg": 0.138, "neu": 0.809, "pos": 0.052, "compound": -0.5106}, "headline": "Morning Agenda: Push to Bolster Banks' Cyberdefenses", "search_term_in_summary": 1, "search_term_in_headline": 0, "headline_summary_senti": {"neg": 0.117, "neu": 0.839, "pos": 0.044, "compound": -0.5106}, "headline_senti": {"neg": 0.0, "neu": 1.0, "pos": 0.0, "compound": 0.0}, "trade_date": "2014-10-22", "lead_paragraph_senti": {"neg": 0.0, "neu": 1.0, "pos": 0.0, "compound": 0.0}, "pub_date": "2014-10-22T07:39:28Z"}, {"summary_senti": {"neg": 0.033, "neu": 0.788, "pos": 0.179, "compound": 0.6597}, "headline": "Today in Small Business: 'We're the Uber of Whatever!'", "search_term_in_summary": 1, "search_term_in_headline": 0, "headline_summary_senti": {"neg": 0.026, "neu": 0.824, "pos": 0.15, "compound": 0.69}, "headline_senti": {"neg": 0.0, "neu": 1.0, "pos": 0.0, "compound": 0.0}, "trade_date": "2014-10-23", "lead_paragraph_senti": {"neg": 0.0, "neu": 1.0, "pos": 0.0, "compound": 0.0}, "pub_date": "2014-10-23T14:34:43Z"}, {"summary_senti": {"neg": 0.0, "neu": 0.909, "pos": 0.091, "compound": 0.5106}, "headline": "Exporting Video From iPhoto", "search_term_in_summary": 1, "search_term_in_headline": 0, "headline_summary_senti": {"neg": 0.0, "neu": 0.918, "pos": 0.082, "compound": 0.5106}, "headline_senti": {"neg": 0.0, "neu": 1.0, "pos": 0.0, "compound": 0.0}, "trade_date": "2014-10-23", "lead_paragraph_senti": {"neg": 0.0, "neu": 1.0, "pos": 0.0, "compound": 0.0}, "pub_date": "2014-10-23T00:00:00Z"}, {"summary_senti": {"neg": 0.177, "neu": 0.823, "pos": 0.0, "compound": -0.4215}, "headline": "Google Executive Makes World Record Jump", "search_term_in_summary": 1, "search_term_in_headline": 1, "headline_summary_senti": {"neg": 0.128, "neu": 0.872, "pos": 0.0, "compound": -0.4215}, "headline_senti": {"neg": 0.0, "neu": 1.0, "pos": 0.0, "compound": 0.0}, "trade_date": "2014-10-24", "lead_paragraph_senti": {"neg": 0.177, "neu": 0.823, "pos": 0.0, "compound": -0.4215}, "pub_date": "2014-10-24T14:06:05Z"}, {"summary_senti": {"neg": 0.0, "neu": 0.797, "pos": 0.203, "compound": 0.4215}, "headline": "With Promotion, Sundar Pichai Becomes Google's Product Chief", "search_term_in_summary": 0, "search_term_in_headline": 1, "headline_summary_senti": {"neg": 0.0, "neu": 0.872, "pos": 0.128, "compound": 0.4215}, "headline_senti": {"neg": 0.0, "neu": 1.0, "pos": 0.0, "compound": 0.0}, "trade_date": "2014-10-25", "lead_paragraph_senti": {"neg": 0.0, "neu": 1.0, "pos": 0.0, "compound": 0.0}, "pub_date": "2014-10-25T16:07:10Z"}, {"summary_senti": {"neg": 0.049, "neu": 0.895, "pos": 0.056, "compound": 0.0516}, "headline": "Parachutist\u2019s Record Fall: Over 25 Miles in 15 Minutes", "search_term_in_summary": 1, "search_term_in_headline": 0, "headline_summary_senti": {"neg": 0.039, "neu": 0.918, "pos": 0.043, "compound": 0.0516}, "headline_senti": {"neg": 0.0, "neu": 1.0, "pos": 0.0, "compound": 0.0}, "trade_date": "2014-10-25", "lead_paragraph_senti": {"neg": 0.15, "neu": 0.85, "pos": 0.0, "compound": -0.5267}, "pub_date": "2014-10-25T00:00:00Z"}, {"summary_senti": {"neg": 0.0, "neu": 1.0, "pos": 0.0, "compound": 0.0}, "headline": "Jennifer Beek, Bradley Hunter", "search_term_in_summary": 1, "search_term_in_headline": 0, "headline_summary_senti": {"neg": 0.0, "neu": 1.0, "pos": 0.0, "compound": 0.0}, "headline_senti": {"neg": 0.0, "neu": 1.0, "pos": 0.0, "compound": 0.0}, "trade_date": "2014-10-26", "lead_paragraph_senti": {"neg": 0.0, "neu": 1.0, "pos": 0.0, "compound": 0.0}, "pub_date": "2014-10-26T00:00:00Z"}, {"summary_senti": {"neg": 0.0, "neu": 0.733, "pos": 0.267, "compound": 0.7184}, "headline": "15 Minutes of Free Fall Required Years of Taming Scientific Challenges", "search_term_in_summary": 1, "search_term_in_headline": 0, "headline_summary_senti": {"neg": 0.0, "neu": 0.711, "pos": 0.289, "compound": 0.8625}, "headline_senti": {"neg": 0.0, "neu": 0.662, "pos": 0.338, "compound": 0.5574}, "trade_date": "2014-10-27", "lead_paragraph_senti": {"neg": 0.0, "neu": 0.733, "pos": 0.267, "compound": 0.7184}, "pub_date": "2014-10-27T00:00:00Z"}, {"summary_senti": {"neg": 0.0, "neu": 1.0, "pos": 0.0, "compound": 0.0}, "headline": "Google Executive Sets Record for Free Fall: Reporter's Notebook", "search_term_in_summary": 1, "search_term_in_headline": 1, "headline_summary_senti": {"neg": 0.0, "neu": 0.907, "pos": 0.093, "compound": 0.5106}, "headline_senti": {"neg": 0.0, "neu": 0.708, "pos": 0.292, "compound": 0.5106}, "trade_date": "2014-10-29", "lead_paragraph_senti": {"neg": 0.0, "neu": 1.0, "pos": 0.0, "compound": 0.0}, "pub_date": "2014-10-29T13:15:29Z"}, {"summary_senti": {"neg": 0.0, "neu": 0.902, "pos": 0.098, "compound": 0.3818}, "headline": "Andy Rubin, Former Head of Android, Departs Google ", "search_term_in_summary": 1, "search_term_in_headline": 1, "headline_summary_senti": {"neg": 0.0, "neu": 0.925, "pos": 0.075, "compound": 0.3818}, "headline_senti": {"neg": 0.0, "neu": 1.0, "pos": 0.0, "compound": 0.0}, "trade_date": "2014-10-31", "lead_paragraph_senti": {"neg": 0.0, "neu": 1.0, "pos": 0.0, "compound": 0.0}, "pub_date": "2014-10-30T21:42:26Z"}, {"summary_senti": {"neg": 0.0, "neu": 0.353, "pos": 0.647, "compound": 0.6705}, "headline": "Google's Analysis of Japan", "search_term_in_summary": 0, "search_term_in_headline": 1, "headline_summary_senti": {"neg": 0.0, "neu": 0.56, "pos": 0.44, "compound": 0.6705}, "headline_senti": {"neg": 0.0, "neu": 1.0, "pos": 0.0, "compound": 0.0}, "trade_date": "2014-10-30", "lead_paragraph_senti": {"neg": 0.0, "neu": 1.0, "pos": 0.0, "compound": 0.0}, "pub_date": "2014-10-30T19:05:08Z"}, {"summary_senti": {"neg": 0.0, "neu": 0.87, "pos": 0.13, "compound": 0.7717}, "headline": "Sorting the Phone\u2019s Address Book", "search_term_in_summary": 1, "search_term_in_headline": 0, "headline_summary_senti": {"neg": 0.0, "neu": 0.882, "pos": 0.118, "compound": 0.7717}, "headline_senti": {"neg": 0.0, "neu": 1.0, "pos": 0.0, "compound": 0.0}, "trade_date": "2014-10-30", "lead_paragraph_senti": {"neg": 0.0, "neu": 1.0, "pos": 0.0, "compound": 0.0}, "pub_date": "2014-10-30T00:00:00Z"}, {"summary_senti": {"neg": 0.085, "neu": 0.82, "pos": 0.095, "compound": 0.0772}, "headline": "The New Thing in Google Flu Trends Is Traditional Data", "search_term_in_summary": 1, "search_term_in_headline": 1, "headline_summary_senti": {"neg": 0.124, "neu": 0.808, "pos": 0.069, "compound": -0.3182}, "headline_senti": {"neg": 0.224, "neu": 0.776, "pos": 0.0, "compound": -0.3818}, "trade_date": "2014-10-31", "lead_paragraph_senti": {"neg": 0.0, "neu": 1.0, "pos": 0.0, "compound": 0.0}, "pub_date": "2014-10-31T15:27:15Z"}, {"summary_senti": {"neg": 0.0, "neu": 0.812, "pos": 0.188, "compound": 0.4019}, "headline": "Tim Cook\u2019s Disclosure That He\u2019s Gay Garners Sweeping Praise", "search_term_in_summary": 1, "search_term_in_headline": 0, "headline_summary_senti": {"neg": 0.0, "neu": 0.767, "pos": 0.233, "compound": 0.743}, "headline_senti": {"neg": 0.0, "neu": 0.69, "pos": 0.31, "compound": 0.5574}, "trade_date": "2014-10-31", "lead_paragraph_senti": {"neg": 0.0, "neu": 0.812, "pos": 0.188, "compound": 0.4019}, "pub_date": "2014-10-31T00:00:00Z"}]